Metadata-Version: 1.2
Name: google-closure-compiler-api
Version: 0.1.4
Summary: Google closure compiler CLI API
Home-page: http://github.com/femtopixel/docker-google-closure-compiler-api
Author: Jay MOULIN
Author-email: jaymoulin@gmail.com
License: MIT
Platform: UNKNOWN
Classifier: Development Status :: 5 - Production/Stable
Classifier: Programming Language :: Python
Classifier: License :: OSI Approved :: MIT License
Classifier: Natural Language :: English
Classifier: Operating System :: OS Independent
Classifier: Programming Language :: Python :: 3
Classifier: Topic :: Multimedia :: Sound/Audio
Requires-Python: >=3
